remotia/__init__.py
remotia/base/__init__.py
remotia/base/common.py
remotia/base/run.py
remotia/base/sched.py
remotia/deployers/__init__.py
remotia/deployers/apt.py
remotia/deployers/common.py
remotia/deployers/db.py
remotia/deployers/file.py
remotia/deployers/internal.py
remotia/deployers/service.py
remotia/deployers/system.py
remotia/deployers/util.py
remotia/scripts/__init__.py
remotia/scripts/common.py
remotia/scripts/consulting.py
remotia/scripts/db.py
remotia/scripts/omni.py
remotia/scripts/operations.py
remotia/templates/hostname.tpl
remotia/templates/interfaces.tpl
remotia/templates/resolv.conf.tpl
remotia-0.2.3.dist-info/top_level.txt
remotia-0.2.3.dist-info/entry_points.txt
remotia-0.2.3.dist-info/METADATA
remotia-0.2.3.dist-info/DESCRIPTION.rst
remotia-0.2.3.dist-info/metadata.json
remotia-0.2.3.dist-info/WHEEL
remotia-0.2.3.dist-info/RECORD
